YanSH/Yan_def.py
YanSH/__init__.py
YanSH-0.1.2.dist-info/LICENSE
YanSH-0.1.2.dist-info/METADATA
YanSH-0.1.2.dist-info/WHEEL
YanSH-0.1.2.dist-info/top_level.txt
YanSH-0.1.2.dist-info/RECORD
